validation_component_bootstrap_utils/__init__.py
validation_component_bootstrap_utils/generate_validation_module.py
validation_component_bootstrap_utils/manager.py
validation_component_bootstrap_utils/conf/config.yaml
validation_component_bootstrap_utils/templates/validation/parser.py
validation_component_bootstrap_utils/templates/validation/record.py
validation_component_bootstrap_utils/templates/validation/validate_file.py
validation_component_bootstrap_utils/templates/validation/validator.py
validation_component_bootstrap_utils-0.5.0.data/scripts/make_executables_and_aliases.py
validation_component_bootstrap_utils-0.5.0.dist-info/AUTHORS.rst
validation_component_bootstrap_utils-0.5.0.dist-info/METADATA
validation_component_bootstrap_utils-0.5.0.dist-info/WHEEL
validation_component_bootstrap_utils-0.5.0.dist-info/entry_points.txt
validation_component_bootstrap_utils-0.5.0.dist-info/top_level.txt
validation_component_bootstrap_utils-0.5.0.dist-info/RECORD
