Metadata-Version: 2.1
Name: validation-component-bootstrap-utils
Version: 0.5.0
Summary: Utilities for Bootstrapping Validation Components
Home-page: https://github.com/jai-python3/validation-component-bootstrap-utils
Author: Jaideep Sundaram
Author-email: jai.python3@gmail.com
Keywords: validation_component_bootstrap_utils
Classifier: Development Status :: 2 - Pre-Alpha
Classifier: Intended Audience :: Developers
Classifier: Natural Language :: English
Classifier: Programming Language :: Python :: 3
Classifier: Programming Language :: Python :: 3.6
Classifier: Programming Language :: Python :: 3.7
Classifier: Programming Language :: Python :: 3.8
Requires-Python: >=3.6
License-File: AUTHORS.rst
Requires-Dist: Click >=7.0
Requires-Dist: PyYAML
Requires-Dist: jinja2
Requires-Dist: Rich
